tests/__init__.py
tests/test_extractor.py
videofacecapture/__init__.py
videofacecapture/face_capture.py
videofacecapture-0.1.0.dist-info/LICENSE
videofacecapture-0.1.0.dist-info/METADATA
videofacecapture-0.1.0.dist-info/WHEEL
videofacecapture-0.1.0.dist-info/top_level.txt
videofacecapture-0.1.0.dist-info/RECORD
