Metadata-Version: 2.2
Name: videofacecapture
Version: 0.1.0
Summary: A library to capture faces from videos and images using OpenCV
Home-page: https://github.com/nazirumar/videofacecapture
Author: Nazir Umar
Author-email: nazirumar888@gmail.com
Classifier: Programming Language :: Python :: 3
Classifier: License :: OSI Approved :: MIT License
Classifier: Operating System :: OS Independent
Requires-Python: >=3.6
License-File: LICENSE
Requires-Dist: opencv-python>=4.5.0
Dynamic: author
Dynamic: author-email
Dynamic: classifier
Dynamic: description
Dynamic: description-content-type
Dynamic: home-page
Dynamic: requires-dist
Dynamic: requires-python
Dynamic: summary
